{
  "_format": "hh-sol-cache-2",
  "files": {
    "C:\\Users\\GUDMAN\\Downloads\\dispute-project\\contracts\\DisputeResolution.sol": {
      "lastModificationDate": 1768717924661,
      "contentHash": "1f59d7e11c2d53a744b52bce7c2b7aee",
      "sourceName": "contracts/DisputeResolution.sol",
      "solcConfig": {
        "version": "0.8.20",
        "settings": {
          "optimizer": {
            "enabled": true,
            "runs": 200
          },
          "viaIR": true,
          "evmVersion": "paris",
          "outputSelection": {
            "*": {
              "*": [
                "abi",
                "evm.bytecode",
                "evm.deployedBytecode",
                "evm.methodIdentifiers",
                "metadata"
              ],
              "": [
                "ast"
              ]
            }
          }
        }
      },
      "imports": [
        "@openzeppelin/contracts/utils/ReentrancyGuard.sol",
        "@openzeppelin/contracts/access/AccessControl.sol",
        "@openzeppelin/contracts/utils/Pausable.sol"
      ],
      "versionPragmas": [
        "^0.8.20"
      ],
      "artifacts": [
        "DisputeResolution"
      ]
    },
    "C:\\Users\\GUDMAN\\Downloads\\node_modules\\@openzeppelin\\contracts\\utils\\ReentrancyGuard.sol": {
      "lastModificationDate": 1768719659056,
      "contentHash": "190613e556d509d9e9a0ea43dc5d891d",
      "sourceName": "@openzeppelin/contracts/utils/ReentrancyGuard.sol",
      "solcConfig": {
        "version": "0.8.20",
        "settings": {
          "optimizer": {
            "enabled": true,
            "runs": 200
          },
          "viaIR": true,
          "evmVersion": "paris",
          "outputSelection": {
            "*": {
              "*": [
                "abi",
                "evm.bytecode",
                "evm.deployedBytecode",
                "evm.methodIdentifiers",
                "metadata"
              ],
              "": [
                "ast"
              ]
            }
          }
        }
      },
      "imports": [],
      "versionPragmas": [
        "^0.8.20"
      ],
      "artifacts": [
        "ReentrancyGuard"
      ]
    },
    "C:\\Users\\GUDMAN\\Downloads\\node_modules\\@openzeppelin\\contracts\\access\\AccessControl.sol": {
      "lastModificationDate": 1768719657183,
      "contentHash": "d0e2c05f09a3aea7cd299bbd4a435ee2",
      "sourceName": "@openzeppelin/contracts/access/AccessControl.sol",
      "solcConfig": {
        "version": "0.8.20",
        "settings": {
          "optimizer": {
            "enabled": true,
            "runs": 200
          },
          "viaIR": true,
          "evmVersion": "paris",
          "outputSelection": {
            "*": {
              "*": [
                "abi",
                "evm.bytecode",
                "evm.deployedBytecode",
                "evm.methodIdentifiers",
                "metadata"
              ],
              "": [
                "ast"
              ]
            }
          }
        }
      },
      "imports": [
        "./IAccessControl.sol",
        "../utils/Context.sol",
        "../utils/introspection/ERC165.sol"
      ],
      "versionPragmas": [
        "^0.8.20"
      ],
      "artifacts": [
        "AccessControl"
      ]
    },
    "C:\\Users\\GUDMAN\\Downloads\\node_modules\\@openzeppelin\\contracts\\utils\\Pausable.sol": {
      "lastModificationDate": 1768719659028,
      "contentHash": "0d47b53e10b1985efbb396f937626279",
      "sourceName": "@openzeppelin/contracts/utils/Pausable.sol",
      "solcConfig": {
        "version": "0.8.20",
        "settings": {
          "optimizer": {
            "enabled": true,
            "runs": 200
          },
          "viaIR": true,
          "evmVersion": "paris",
          "outputSelection": {
            "*": {
              "*": [
                "abi",
                "evm.bytecode",
                "evm.deployedBytecode",
                "evm.methodIdentifiers",
                "metadata"
              ],
              "": [
                "ast"
              ]
            }
          }
        }
      },
      "imports": [
        "../utils/Context.sol"
      ],
      "versionPragmas": [
        "^0.8.20"
      ],
      "artifacts": [
        "Pausable"
      ]
    },
    "C:\\Users\\GUDMAN\\Downloads\\node_modules\\@openzeppelin\\contracts\\utils\\Context.sol": {
      "lastModificationDate": 1768719657501,
      "contentHash": "67bfbc07588eb8683b3fd8f6f909563e",
      "sourceName": "@openzeppelin/contracts/utils/Context.sol",
      "solcConfig": {
        "version": "0.8.20",
        "settings": {
          "optimizer": {
            "enabled": true,
            "runs": 200
          },
          "viaIR": true,
          "evmVersion": "paris",
          "outputSelection": {
            "*": {
              "*": [
                "abi",
                "evm.bytecode",
                "evm.deployedBytecode",
                "evm.methodIdentifiers",
                "metadata"
              ],
              "": [
                "ast"
              ]
            }
          }
        }
      },
      "imports": [],
      "versionPragmas": [
        "^0.8.20"
      ],
      "artifacts": [
        "Context"
      ]
    },
    "C:\\Users\\GUDMAN\\Downloads\\node_modules\\@openzeppelin\\contracts\\access\\IAccessControl.sol": {
      "lastModificationDate": 1768719658521,
      "contentHash": "def1e8f7b6cac577cf2600655bf3bdf8",
      "sourceName": "@openzeppelin/contracts/access/IAccessControl.sol",
      "solcConfig": {
        "version": "0.8.20",
        "settings": {
          "optimizer": {
            "enabled": true,
            "runs": 200
          },
          "viaIR": true,
          "evmVersion": "paris",
          "outputSelection": {
            "*": {
              "*": [
                "abi",
                "evm.bytecode",
                "evm.deployedBytecode",
                "evm.methodIdentifiers",
                "metadata"
              ],
              "": [
                "ast"
              ]
            }
          }
        }
      },
      "imports": [],
      "versionPragmas": [
        ">=0.8.4"
      ],
      "artifacts": [
        "IAccessControl"
      ]
    },
    "C:\\Users\\GUDMAN\\Downloads\\node_modules\\@openzeppelin\\contracts\\utils\\introspection\\ERC165.sol": {
      "lastModificationDate": 1768719658039,
      "contentHash": "0906d06dca25210d4696dcef6dad2909",
      "sourceName": "@openzeppelin/contracts/utils/introspection/ERC165.sol",
      "solcConfig": {
        "version": "0.8.20",
        "settings": {
          "optimizer": {
            "enabled": true,
            "runs": 200
          },
          "viaIR": true,
          "evmVersion": "paris",
          "outputSelection": {
            "*": {
              "*": [
                "abi",
                "evm.bytecode",
                "evm.deployedBytecode",
                "evm.methodIdentifiers",
                "metadata"
              ],
              "": [
                "ast"
              ]
            }
          }
        }
      },
      "imports": [
        "./IERC165.sol"
      ],
      "versionPragmas": [
        "^0.8.20"
      ],
      "artifacts": [
        "ERC165"
      ]
    },
    "C:\\Users\\GUDMAN\\Downloads\\node_modules\\@openzeppelin\\contracts\\utils\\introspection\\IERC165.sol": {
      "lastModificationDate": 1768719658658,
      "contentHash": "7074c93b1ea0a122063f26ddd1db1032",
      "sourceName": "@openzeppelin/contracts/utils/introspection/IERC165.sol",
      "solcConfig": {
        "version": "0.8.20",
        "settings": {
          "optimizer": {
            "enabled": true,
            "runs": 200
          },
          "viaIR": true,
          "evmVersion": "paris",
          "outputSelection": {
            "*": {
              "*": [
                "abi",
                "evm.bytecode",
                "evm.deployedBytecode",
                "evm.methodIdentifiers",
                "metadata"
              ],
              "": [
                "ast"
              ]
            }
          }
        }
      },
      "imports": [],
      "versionPragmas": [
        ">=0.4.16"
      ],
      "artifacts": [
        "IERC165"
      ]
    },
    "C:\\Users\\GUDMAN\\Downloads\\node_modules\\@openzeppelin\\contracts\\access\\Ownable.sol": {
      "lastModificationDate": 1768719658980,
      "contentHash": "d3c790edc9ccf808a17c5a6cd13614fd",
      "sourceName": "@openzeppelin/contracts/access/Ownable.sol",
      "solcConfig": {
        "version": "0.8.20",
        "settings": {
          "optimizer": {
            "enabled": true,
            "runs": 200
          },
          "viaIR": true,
          "evmVersion": "paris",
          "outputSelection": {
            "*": {
              "*": [
                "abi",
                "evm.bytecode",
                "evm.deployedBytecode",
                "evm.methodIdentifiers",
                "metadata"
              ],
              "": [
                "ast"
              ]
            }
          }
        }
      },
      "imports": [
        "../utils/Context.sol"
      ],
      "versionPragmas": [
        "^0.8.20"
      ],
      "artifacts": [
        "Ownable"
      ]
    },
    "C:\\Users\\GUDMAN\\Downloads\\dispute-project\\contracts\\GenLayerOracleAdapter.sol": {
      "lastModificationDate": 1768717924663,
      "contentHash": "24e5eaa094c21fe280b1310ea80fe24a",
      "sourceName": "contracts/GenLayerOracleAdapter.sol",
      "solcConfig": {
        "version": "0.8.20",
        "settings": {
          "optimizer": {
            "enabled": true,
            "runs": 200
          },
          "viaIR": true,
          "evmVersion": "paris",
          "outputSelection": {
            "*": {
              "*": [
                "abi",
                "evm.bytecode",
                "evm.deployedBytecode",
                "evm.methodIdentifiers",
                "metadata"
              ],
              "": [
                "ast"
              ]
            }
          }
        }
      },
      "imports": [
        "@openzeppelin/contracts/access/Ownable.sol",
        "@openzeppelin/contracts/utils/ReentrancyGuard.sol"
      ],
      "versionPragmas": [
        "^0.8.20"
      ],
      "artifacts": [
        "GenLayerOracleAdapter",
        "IDisputeResolution"
      ]
    },
    "C:\\Users\\GUDMAN\\Downloads\\dispute-project\\contracts\\ReputationSystem.sol": {
      "lastModificationDate": 1768717924666,
      "contentHash": "344e26fb6206fc8e5f66db978d7a3af4",
      "sourceName": "contracts/ReputationSystem.sol",
      "solcConfig": {
        "version": "0.8.20",
        "settings": {
          "optimizer": {
            "enabled": true,
            "runs": 200
          },
          "viaIR": true,
          "evmVersion": "paris",
          "outputSelection": {
            "*": {
              "*": [
                "abi",
                "evm.bytecode",
                "evm.deployedBytecode",
                "evm.methodIdentifiers",
                "metadata"
              ],
              "": [
                "ast"
              ]
            }
          }
        }
      },
      "imports": [
        "@openzeppelin/contracts/access/AccessControl.sol",
        "@openzeppelin/contracts/utils/ReentrancyGuard.sol"
      ],
      "versionPragmas": [
        "^0.8.20"
      ],
      "artifacts": [
        "ReputationSystem"
      ]
    },
    "C:\\Users\\GUDMAN\\Downloads\\node_modules\\@openzeppelin\\contracts\\interfaces\\IERC165.sol": {
      "lastModificationDate": 1768719658647,
      "contentHash": "947853028399b7de34bcc3704ee06e99",
      "sourceName": "@openzeppelin/contracts/interfaces/IERC165.sol",
      "solcConfig": {
        "version": "0.8.20",
        "settings": {
          "optimizer": {
            "enabled": true,
            "runs": 200
          },
          "viaIR": true,
          "evmVersion": "paris",
          "outputSelection": {
            "*": {
              "*": [
                "abi",
                "evm.bytecode",
                "evm.deployedBytecode",
                "evm.methodIdentifiers",
                "metadata"
              ],
              "": [
                "ast"
              ]
            }
          }
        }
      },
      "imports": [
        "../utils/introspection/IERC165.sol"
      ],
      "versionPragmas": [
        ">=0.4.16"
      ],
      "artifacts": []
    },
    "C:\\Users\\GUDMAN\\Downloads\\node_modules\\@openzeppelin\\contracts\\interfaces\\IERC1363.sol": {
      "lastModificationDate": 1768719658625,
      "contentHash": "a7fd0f05e36b0d0a21c75340c9c639ec",
      "sourceName": "@openzeppelin/contracts/interfaces/IERC1363.sol",
      "solcConfig": {
        "version": "0.8.20",
        "settings": {
          "optimizer": {
            "enabled": true,
            "runs": 200
          },
          "viaIR": true,
          "evmVersion": "paris",
          "outputSelection": {
            "*": {
              "*": [
                "abi",
                "evm.bytecode",
                "evm.deployedBytecode",
                "evm.methodIdentifiers",
                "metadata"
              ],
              "": [
                "ast"
              ]
            }
          }
        }
      },
      "imports": [
        "./IERC20.sol",
        "./IERC165.sol"
      ],
      "versionPragmas": [
        ">=0.6.2"
      ],
      "artifacts": [
        "IERC1363"
      ]
    },
    "C:\\Users\\GUDMAN\\Downloads\\node_modules\\@openzeppelin\\contracts\\interfaces\\IERC20.sol": {
      "lastModificationDate": 1768719658684,
      "contentHash": "68620db2da7583d9a4919096ac77f577",
      "sourceName": "@openzeppelin/contracts/interfaces/IERC20.sol",
      "solcConfig": {
        "version": "0.8.20",
        "settings": {
          "optimizer": {
            "enabled": true,
            "runs": 200
          },
          "viaIR": true,
          "evmVersion": "paris",
          "outputSelection": {
            "*": {
              "*": [
                "abi",
                "evm.bytecode",
                "evm.deployedBytecode",
                "evm.methodIdentifiers",
                "metadata"
              ],
              "": [
                "ast"
              ]
            }
          }
        }
      },
      "imports": [
        "../token/ERC20/IERC20.sol"
      ],
      "versionPragmas": [
        ">=0.4.16"
      ],
      "artifacts": []
    },
    "C:\\Users\\GUDMAN\\Downloads\\node_modules\\@openzeppelin\\contracts\\token\\ERC20\\IERC20.sol": {
      "lastModificationDate": 1768719658691,
      "contentHash": "9261adf6457863de3e9892f51317ec89",
      "sourceName": "@openzeppelin/contracts/token/ERC20/IERC20.sol",
      "solcConfig": {
        "version": "0.8.20",
        "settings": {
          "optimizer": {
            "enabled": true,
            "runs": 200
          },
          "viaIR": true,
          "evmVersion": "paris",
          "outputSelection": {
            "*": {
              "*": [
                "abi",
                "evm.bytecode",
                "evm.deployedBytecode",
                "evm.methodIdentifiers",
                "metadata"
              ],
              "": [
                "ast"
              ]
            }
          }
        }
      },
      "imports": [],
      "versionPragmas": [
        ">=0.4.16"
      ],
      "artifacts": [
        "IERC20"
      ]
    },
    "C:\\Users\\GUDMAN\\Downloads\\node_modules\\@openzeppelin\\contracts\\token\\ERC20\\utils\\SafeERC20.sol": {
      "lastModificationDate": 1768719659091,
      "contentHash": "1fb9edee1d763745a62d0b1954998792",
      "sourceName": "@openzeppelin/contracts/token/ERC20/utils/SafeERC20.sol",
      "solcConfig": {
        "version": "0.8.20",
        "settings": {
          "optimizer": {
            "enabled": true,
            "runs": 200
          },
          "viaIR": true,
          "evmVersion": "paris",
          "outputSelection": {
            "*": {
              "*": [
                "abi",
                "evm.bytecode",
                "evm.deployedBytecode",
                "evm.methodIdentifiers",
                "metadata"
              ],
              "": [
                "ast"
              ]
            }
          }
        }
      },
      "imports": [
        "../IERC20.sol",
        "../../../interfaces/IERC1363.sol"
      ],
      "versionPragmas": [
        "^0.8.20"
      ],
      "artifacts": [
        "SafeERC20"
      ]
    },
    "C:\\Users\\GUDMAN\\Downloads\\dispute-project\\contracts\\MultiTokenDisputeResolution.sol": {
      "lastModificationDate": 1768717924665,
      "contentHash": "68b0c755855e8da76a937a23b2bedac9",
      "sourceName": "contracts/MultiTokenDisputeResolution.sol",
      "solcConfig": {
        "version": "0.8.20",
        "settings": {
          "optimizer": {
            "enabled": true,
            "runs": 200
          },
          "viaIR": true,
          "evmVersion": "paris",
          "outputSelection": {
            "*": {
              "*": [
                "abi",
                "evm.bytecode",
                "evm.deployedBytecode",
                "evm.methodIdentifiers",
                "metadata"
              ],
              "": [
                "ast"
              ]
            }
          }
        }
      },
      "imports": [
        "@openzeppelin/contracts/token/ERC20/IERC20.sol",
        "@openzeppelin/contracts/token/ERC20/utils/SafeERC20.sol",
        "@openzeppelin/contracts/utils/ReentrancyGuard.sol",
        "@openzeppelin/contracts/access/AccessControl.sol",
        "@openzeppelin/contracts/utils/Pausable.sol"
      ],
      "versionPragmas": [
        "^0.8.20"
      ],
      "artifacts": [
        "IERC20Metadata",
        "MultiTokenDisputeResolution"
      ]
    },
    "C:\\Users\\GUDMAN\\Downloads\\dispute-project\\contracts\\EvidenceManager.sol": {
      "lastModificationDate": 1768717924662,
      "contentHash": "ef453f56df8a041e89385ea1fa67756e",
      "sourceName": "contracts/EvidenceManager.sol",
      "solcConfig": {
        "version": "0.8.20",
        "settings": {
          "optimizer": {
            "enabled": true,
            "runs": 200
          },
          "viaIR": true,
          "evmVersion": "paris",
          "outputSelection": {
            "*": {
              "*": [
                "abi",
                "evm.bytecode",
                "evm.deployedBytecode",
                "evm.methodIdentifiers",
                "metadata"
              ],
              "": [
                "ast"
              ]
            }
          }
        }
      },
      "imports": [
        "@openzeppelin/contracts/access/AccessControl.sol",
        "@openzeppelin/contracts/utils/ReentrancyGuard.sol"
      ],
      "versionPragmas": [
        "^0.8.20"
      ],
      "artifacts": [
        "EvidenceManager"
      ]
    }
  }
}
